LICENSE
MANIFEST.in
setup.py
inspectmodel/__init__.py
inspectmodel/conf.py
inspectmodel/urls.py
inspectmodel/views.py
inspectmodel/static/inspectmodel/css/inspect.css
inspectmodel/static/inspectmodel/css/smoothness/jquery-ui-1.10.4.custom.min.css
inspectmodel/static/inspectmodel/css/smoothness/images/animated-overlay.gif
inspectmodel/static/inspectmodel/css/smoothness/images/ui-bg_flat_0_aaaaaa_40x100.png
inspectmodel/static/inspectmodel/css/smoothness/images/ui-bg_flat_75_ffffff_40x100.png
inspectmodel/static/inspectmodel/css/smoothness/images/ui-bg_glass_55_fbf9ee_1x400.png
inspectmodel/static/inspectmodel/css/smoothness/images/ui-bg_glass_65_ffffff_1x400.png
inspectmodel/static/inspectmodel/css/smoothness/images/ui-bg_glass_75_dadada_1x400.png
inspectmodel/static/inspectmodel/css/smoothness/images/ui-bg_glass_75_e6e6e6_1x400.png
inspectmodel/static/inspectmodel/css/smoothness/images/ui-bg_glass_95_fef1ec_1x400.png
inspectmodel/static/inspectmodel/css/smoothness/images/ui-bg_highlight-soft_75_cccccc_1x100.png
inspectmodel/static/inspectmodel/css/smoothness/images/ui-icons_222222_256x240.png
inspectmodel/static/inspectmodel/css/smoothness/images/ui-icons_2e83ff_256x240.png
inspectmodel/static/inspectmodel/css/smoothness/images/ui-icons_454545_256x240.png
inspectmodel/static/inspectmodel/css/smoothness/images/ui-icons_888888_256x240.png
inspectmodel/static/inspectmodel/css/smoothness/images/ui-icons_cd0a0a_256x240.png
inspectmodel/static/inspectmodel/js/inspect.js
inspectmodel/static/inspectmodel/js/jquery-2.1.0.min.js
inspectmodel/static/inspectmodel/js/jquery-ui-1.10.4.custom.min.js
inspectmodel/templates/included_item_inspected.html
inspectmodel/templates/upy_inspect_browse.html
inspectmodel/templatetags/__init__.py
inspectmodel/templatetags/inspect_tags.py
twentytab_inspectmodel.egg-info/PKG-INFO
twentytab_inspectmodel.egg-info/SOURCES.txt
twentytab_inspectmodel.egg-info/dependency_links.txt
twentytab_inspectmodel.egg-info/requires.txt
twentytab_inspectmodel.egg-info/top_level.txt