Metadata-Version: 1.0
Name: twentytab-inspectmodel
Version: 0.1
Summary: A django app based on django-inspect-model that implements a user interface to inspect all models in your applications
Home-page: https://github.com/20tab/twentytab-inspectmodel
Author: 20tab S.r.l.
Author-email: info@20tab.com
License: MIT License
Platform: UNKNOWN
